fastapi_querybuilder/__init__.py
fastapi_querybuilder/builder.py
fastapi_querybuilder/core.py
fastapi_querybuilder/dependencies.py
fastapi_querybuilder/operators.py
fastapi_querybuilder/params.py
fastapi_querybuilder/py.typed
fastapi_querybuilder/utils.py
fastapi_querybuilder-0.1.13.dist-info/METADATA
fastapi_querybuilder-0.1.13.dist-info/WHEEL
fastapi_querybuilder-0.1.13.dist-info/licenses/LICENSE
fastapi_querybuilder-0.1.13.dist-info/RECORD
