Metadata-Version: 2.4
Name: fastapi-querybuilder
Version: 0.1.13
Summary: Smart filtering, sorting, and searching for FastAPI with SQLAlchemy
License: MIT
License-File: LICENSE
Keywords: fastapi,sqlalchemy,filters,query,sort,search,pagination,api,rest
Author: Bhadri01
Author-email: bhadrinathan28@gmail.com
Requires-Python: >=3.10,<4.0
Classifier: Framework :: FastAPI
Classifier: License :: OSI Approved :: MIT License
Classifier: Operating System :: OS Independent
Classifier: Programming Language :: Python :: 3
Classifier: Programming Language :: Python :: 3.10
Classifier: Programming Language :: Python :: 3.11
Classifier: Programming Language :: Python :: 3.12
Classifier: Programming Language :: Python :: 3.13
Classifier: Programming Language :: Python :: 3.14
Requires-Dist: aiosqlite (>=0.21.0)
Requires-Dist: fastapi (>=0.115)
Requires-Dist: fastapi_pagination (>=0.13.2)
Requires-Dist: poetry (>=2.1.4)
Requires-Dist: sqlalchemy (>=2.0)
Requires-Dist: uvicorn (>=0.30)
Project-URL: Repository, https://github.com/bhadri01/fastapi-querybuilder
